lawnlp/__init__.py
lawnlp/hello.py
lawnlp-0.0.1.dist-info/LICENSE
lawnlp-0.0.1.dist-info/METADATA
lawnlp-0.0.1.dist-info/WHEEL
lawnlp-0.0.1.dist-info/top_level.txt
lawnlp-0.0.1.dist-info/RECORD
