Metadata-Version: 2.1
Name: lawnlp
Version: 0.0.1
Summary: An open-source law package,aiming at Narrating Law just using Python.
Home-page: https://cpanlp.com
Author: Draco Deng
Author-email: dracodeng6@gmail.com
License: MIT
Keywords: python,law,intelligent law,linguistic turn,linguistic
Classifier: Intended Audience :: Developers
Classifier: License :: OSI Approved :: MIT License
Classifier: Programming Language :: Python :: 3
Classifier: Operating System :: Unix
Classifier: Operating System :: MacOS :: MacOS X
Classifier: Operating System :: Microsoft :: Windows
Classifier: Natural Language :: English
Classifier: Natural Language :: Chinese (Simplified)
License-File: LICENSE
